sortlib/__init__.py
sortlib/sorting.py
sortlib-1.5.0.dist-info/LICENSE
sortlib-1.5.0.dist-info/METADATA
sortlib-1.5.0.dist-info/WHEEL
sortlib-1.5.0.dist-info/top_level.txt
sortlib-1.5.0.dist-info/RECORD
