Metadata-Version: 2.1
Name: sortlib
Version: 1.5.0
Summary: Библиотека для сортировки с использованием различных алгоритмов.
Author: Vanek
Author-email: firi8228@gmail.com
Classifier: Programming Language :: Python :: 3
Classifier: License :: OSI Approved :: MIT License
Classifier: Operating System :: OS Independent
Requires-Python: >=3.6
License-File: LICENSE
